qwik_tern/__init__.py
qwik_tern/connection.py
qwik_tern/logger.py
qwik_tern/migration.py
qwik_tern-0.0.6.dist-info/METADATA
qwik_tern-0.0.6.dist-info/WHEEL
qwik_tern-0.0.6.dist-info/licenses/LICENSE
qwik_tern-0.0.6.dist-info/RECORD
