Metadata-Version: 2.3
Name: qwik-tern
Version: 0.0.6
Summary: This project is a database migration tool that helps manage and apply database schema changes. It uses a JSON file to define the changes and applies them to a MySQL database.
Project-URL: Homepage, https://github.com/nimaidev/tern
Author-email: Nimai C <nimaic.dev@gmail.com>
License-File: LICENSE
Classifier: License :: OSI Approved :: MIT License
Classifier: Programming Language :: Python :: 3
Requires-Python: >=3.8
